src/__init__.py
src/core.py
src/main.py
src/scenario.py
intro_python_101-0.1.2.dist-info/METADATA
intro_python_101-0.1.2.dist-info/WHEEL
intro_python_101-0.1.2.dist-info/RECORD
